LICENSE.txt
README.md
setup.py
sam_algorithm.egg-info/PKG-INFO
sam_algorithm.egg-info/SOURCES.txt
sam_algorithm.egg-info/dependency_links.txt
sam_algorithm.egg-info/not-zip-safe
sam_algorithm.egg-info/requires.txt
sam_algorithm.egg-info/top_level.txt
samalg/__init__.py
samalg/gui.py
samalg/utilities.py
test/test_sam.py