Metadata-Version: 2.1
Name: sam-algorithm
Version: 1.0.2
Summary: The Self-Assembling-Manifold algorithm
Home-page: https://github.com/atarashansky/self-assembling-manifold
Author: Alexander J. Tarashansky
Author-email: tarashan@stanford.edu
License: UNKNOWN
Keywords: scrnaseq analysis manifold reconstruction
Platform: UNKNOWN
Requires-Python: >=3.6
Provides-Extra: louvain
Provides-Extra: leiden
Provides-Extra: hdbscan
Provides-Extra: plot
Provides-Extra: scanpy
License-File: LICENSE.txt
